wstrade/__init__.py
wstrade/main.py
WSTrade_alhparsa-0.0.1a2.dist-info/LICENSE
WSTrade_alhparsa-0.0.1a2.dist-info/METADATA
WSTrade_alhparsa-0.0.1a2.dist-info/WHEEL
WSTrade_alhparsa-0.0.1a2.dist-info/top_level.txt
WSTrade_alhparsa-0.0.1a2.dist-info/RECORD
