Metadata-Version: 2.1
Name: WSTrade-alhparsa
Version: 0.0.1a2
Summary: A wrapper for WS Trade API to remotely execute orders
Home-page: https://github.com/alhparsa/wstrade-python-wrapper-api
Author: Parsa Alamzadeh
Author-email: alh.parsa@gmail.com
License: UNKNOWN
Platform: UNKNOWN
Classifier: Programming Language :: Python :: 3
Classifier: License :: OSI Approved :: MIT License
Classifier: Operating System :: OS Independent
Requires-Python: >=3.6
